face_pose.py
face_pose-0.0.3.dist-info/DESCRIPTION.rst
face_pose-0.0.3.dist-info/METADATA
face_pose-0.0.3.dist-info/RECORD
face_pose-0.0.3.dist-info/WHEEL
face_pose-0.0.3.dist-info/metadata.json
face_pose-0.0.3.dist-info/top_level.txt
