Metadata-Version: 2.0
Name: face-pose
Version: 0.0.3
Summary: get the facepose
Home-page: http://www.zhaomingming.cn
Author: zhaomingming
Author-email: 13271929138@163.com
License: MIT
Platform: any
